[{"product":"","address":"a@a.a","delivery":"","payment":"Card","status":"Declined","declineReason":"3","orderDate":"04-01-2018","buyerEmail":"a@a.a","buyerName":"a@a.a","options":"[{\"product\":\"Lenovo 1\",\"amount\":6}]","id":1},{"product":"","address":"t@t.t","delivery":"","payment":"Card","status":"In Process","declineReason":"","orderDate":"04-01-2018","buyerEmail":"t@t.t","buyerName":"t@t.t","options":"[{\"product\":\"Lenovo 2\",\"amount\":4},{\"product\":\"Samsung 1\",\"amount\":3}]","id":2},{"address":"a@a.a","delivery":"On The Way","payment":"Card","status":"In Process","declineReason":"","orderDate":"05-01-2018","buyerEmail":"a@a.a","buyerName":"a@a.a","options":"[{\"product\":\"Lenovo 1\",\"amount\":1},{\"product\":\"Lenovo 2\",\"amount\":1},{\"product\":\"Samsung 1\",\"amount\":1}]","id":3},{"address":"a@a.a","delivery":"On The Way","payment":"Card","status":"Declined","declineReason":"kk","orderDate":"05-01-2018","buyerEmail":"a@a.a","buyerName":"a@a.a","options":"[{\"product\":\"Lenovo 1\",\"amount\":1},{\"product\":\"Lenovo 2\",\"amount\":1},{\"product\":\"Samsung 1\",\"amount\":1}]","id":4},{"address":"a@a.a","delivery":"On The Way","payment":"Card","status":"In Process","declineReason":"","orderDate":"05-01-2018","buyerEmail":"a@a.a","buyerName":"a@a.a","options":"[{\"product\":\"Lenovo 1\",\"amount\":1},{\"product\":\"Lenovo 2\",\"amount\":1},{\"product\":\"Samsung 1\",\"amount\":1}]","id":5},{"address":"a@a.a","delivery":"On The Way","payment":"Card","status":"In Process","declineReason":"","orderDate":"05-01-2018","buyerEmail":"a@a.a","buyerName":"a@a.a","options":"[{\"product\":\"Lenovo 1\",\"amount\":1},{\"product\":\"Lenovo 2\",\"amount\":1},{\"product\":\"Samsung 1\",\"amount\":1}]","id":6},{"address":"a@a.a","delivery":"On The Way","payment":"Card","status":"In Process","declineReason":"","orderDate":"05-01-2018","buyerEmail":"a@a.a","buyerName":"a@a.a","options":"[{\"product\":\"Lenovo 1\",\"amount\":1},{\"product\":\"Lenovo 2\",\"amount\":1},{\"product\":\"Samsung 1\",\"amount\":1}]","id":7},{"address":"a@a.a","delivery":"On The Way","payment":"Card","status":"In Process","declineReason":"","orderDate":"09-01-2018","buyerEmail":"a@a.a","buyerName":"a@a.a","options":"[{\"product\":\"Lenovo 1\",\"amount\":1},{\"product\":\"Lenovo 2\",\"amount\":1},{\"product\":\"Samsung 1\",\"amount\":1},{\"product\":\"Samsung 2\",\"amount\":1}]","id":8},{"address":"b@b.b","deliveryType":"On The Way","paymentType":"Card","status":"In Process","declineReason":"","orderDate":"15-01-2018","buyerEmail":"b@b.b","buyerName":"b@b.b","options":"[{\"product\":\"Lenovo 2\",\"amount\":2},{\"product\":\"Samsung 1\",\"amount\":1},{\"product\":\"Lenovo 1\",\"amount\":1}]","id":9},{"address":"b@b.b","deliveryType":"On The Way","paymentType":"Card","status":"In Process","declineReason":"","orderDate":"15-01-2018","buyerEmail":"b@b.b","buyerName":"b@b.b","options":"[{\"product\":\"Xiaomi 2\",\"amount\":2}]","id":10},{"address":"b@b.b","deliveryType":"On The Way","paymentType":"Card","status":"In Process","declineReason":"","orderDate":"15-01-2018","buyerEmail":"b@b.b","buyerName":"b@b.b","options":"[{\"product\":\"Lenovo 1\",\"amount\":1}]","id":11},{"address":"b@b.b","deliveryType":"On The Way","paymentType":"Card","status":"In Process","declineReason":"","orderDate":"15-01-2018","buyerEmail":"b@b.b","buyerName":"b@b.b","options":"[]","id":12},{"address":"r@r.r","deliveryType":"On The Way","paymentType":"Card","status":"In Process","declineReason":"","orderDate":"16-01-2018","buyerEmail":"r@r.r","buyerName":"r@r.r","options":"[{\"product\":\"Lenovo 2\",\"amount\":2}]","id":13},{"address":"1@1.1","deliveryType":"On The Way","paymentType":"Card","status":"In Process","declineReason":"","orderDate":"16-01-2018","buyerEmail":"1@1.1","buyerName":"1@1.1","options":"[{\"product\":\"Lenovo 1\",\"amount\":1}]","id":14},{"address":"1@1.1","deliveryType":"On The Way","paymentType":"Card","status":"In Process","declineReason":"","orderDate":"16-01-2018","buyerEmail":"1@1.1","buyerName":"1@1.1","options":"[{\"product\":\"Lenovo 1\",\"amount\":4}]","id":15}]